imapmon/channels/base.py
imapmon/channels/tg.py
imapmon-0.6.70.dist-info/LICENSE
imapmon-0.6.70.dist-info/METADATA
imapmon-0.6.70.dist-info/WHEEL
imapmon-0.6.70.dist-info/entry_points.txt
imapmon-0.6.70.dist-info/top_level.txt
imapmon-0.6.70.dist-info/RECORD
