Metadata-Version: 2.1
Name: imapmon
Version: 0.6.70
Summary: Tool for monitoring IMAP mailboxes and retransmitting received emails via alternative channels
Home-page: https://soar.name
Author: soar
Author-email: i@soar.name
License: MIT
Keywords: imap,telegram
Classifier: Development Status :: 5 - Production/Stable
Classifier: Intended Audience :: Developers
Classifier: License :: OSI Approved :: MIT License
Classifier: Operating System :: OS Independent
Classifier: Programming Language :: Python
Classifier: Programming Language :: Python :: 3 :: Only
Classifier: Programming Language :: Python :: 3.7
Classifier: Programming Language :: Python :: 3.8
Classifier: Programming Language :: Python :: 3.9
Classifier: Programming Language :: Python :: 3.10
License-File: LICENSE
